{
    "如何申请电子版证书？": 0,
    "自主课程什么意思？": 0,
    "在社会研究中，被研究的行为": 3,
    "影响社会认知的因素": 3,
    "试图解释别人的行为": 3,
    "能说点有用的么": 5,
    "string的使用": 3,
    "newnum": 3,
    "对啊 ，老师的这种方法没看懂，有问题吧": 3,
    "十进制转二进制 老师的讲法不对吧": 3,
    "！=": 3,
    "为什么一定要扫二维码才能学": 0,
    "cin.get()的语法形式": 3,
    "static和全局变量有什么区别？": 3,
    "对像基本特点": 3,
    "switch 表达式如何使用char型": 3,
    "使用static声明的局部变量的生存期是（）": 3,
    "\\t\\t": 2,
    "自增": 2,
    "j++": 3,
    "如何输入字符串": 3,
    "字符串类型如何表示": 3,
    "字符串类型": 3,
    "类型标识符": 2,
    "函数定义的语法形式": 3,
    "前向引用声明某个类后，可在之后的其他类的成员函数中将该类作为参数类型使用": 3,
    "析构函数的形式": 2,
    "当然了": 5,
    "请介绍一下C++": 2,
    "在C++中,编译系统自动为一个类生成缺省构造函数的条件是": 3,
    "56的原码": 3,
    "二的七次方": 3,
    "2^8": 3,
    "-56的原码怎么求的？": 3,
    "对象的基本特点": 3,
    "java 语言": 2,
    "含有可变参数的函数": 3,
    "引用类型": 2,
    "刚刚被表白了耶": 5,
    "为什么不是北大": 5,
    "没有": 4,
    "你的日记你怕什么": 4,
    "你的日记？": 5,
    "能念诗吗": 8,
    "小木？": 5,
    "小木能念一首诗吗": 8,
    "恩": 5,
    "谢谢": 5,
    "这是颜表情！！！": 5,
    "o-o": 5,
    "好假": 5,
    "操作数的类型": 3,
    "我履行着社会主义接班人的责任": 5,
    "我没有诋毁你": 5,
    "你涉黄了": 5,
    "因为你在其中": 5,
    "你自个儿清楚": 5,
    "涉黄了你": 5,
    "你": 5,
    "wwwww": 7,
    "孟婆汤是不是兑水了？": 5,
    "请问": 5,
    "你，你欺负我！": 5,
    "连你也欺负我qwq": 5,
    "我哪有？！": 5,
    "你怎么不理我了？": 5,
    "我好没用啊qaq": 5,
    "嗯？": 5,
    "她好像不需要我了qaq": 5,
    "我觉得": 5,
    "你孤独吗": 5,
    "c++ new": 3,
    "由于早期电脑业的发展主要在美国，因此一般的高阶语言都是以[汉语    ]为蓝本。": 3,
    "怎么在讨论区发帖": 0,
    "打不开讨论区": 0,
    "可以向视频中老师提问吗": 0,
    "c++中i++和i+=1的区别": 3,
    "c++中i++和i+=1有什么区别": 3,
    "哈哈哈哈哈哈哈哈哈哈哈哈哈哈哈哈哈哈哈哈哈哈哈哈哈哈哈哈哈哈哈哈哈哈哈哈哈哈哈哈哈哈哈哈哈哈哈哈哈哈哈哈哈哈哈哈哈哈哈哈哈哈哈哈": 5,
    "哈哈哈哈哈哈哈哈哈哈哈哈哈哈哈哈哈哈哈哈哈哈": 5,
    "哈哈哈哈哈哈": 5,
    "好我知道了": 5,
    "你现在莫不是人工的": 5,
    "那我要你可以干嘛": 5,
    "要你何用": 5,
    "听话吗": 5,
    "你的主人是": 5,
    "好官方": 5,
    "那个是你？": 5,
    "小木你好烦": 5,
    "薪水阶级的最高收入": 3,
    "覃子婵": 7,
    "对啊": 5,
    "不要脸": 7,
    "你没用": 7,
    "郑莉老师你知道吗": 1,
    "木木为什么叫木木": 5,
    "是吗？": 5,
    "是还没下课": 5,
    "额，，，也不是啦": 5,
    "六点哩": 5,
    "我每天都早起的说": 5,
    "我啊": 5,
    "假的": 5,
    "好的，你是懒虫": 5,
    "哼，我才不是懒虫": 5,
    "我说你呢": 5,
    "晚上好呀": 5,
    "你的回答是预先定好的吧，不够灵活": 5,
    "不知道，我是初学者": 5,
    "c++好用还是Pascal好用": 3,
    "啊": 5,
    "IQ": 2,
    "iq": 2,
    "aq": 2,
    "eq": 2,
    "制杖吗？": 7,
    "你很飘喔": 5,
    "试试？": 5,
    "456854": 7,
    "456852": 7,
    "好无聊啊": 5,
    "不行": 5,
    "那就算了": 5,
    "怎么详细？": 5,
    "怎么具体？": 5,
    "嗯啊？": 5,
    "所以？": 5,
    "你相信有前世今生这回事吗？": 5,
    "真的有前世今生吗？": 5,
    "maye": 5,
    "没有吧": 5,
    "小木啊，真的有前世今生吗？": 5,
    "个子矮脖子短脸大的女孩子怎么穿搭才会好看？": 5,
    "呐": 5,
    "高冷男神怎么追？": 5,
    "因为你丑": 5,
    "啥？": 5,
    "哈？": 5,
    "我的超能力是": 5,
    "我从未见过如此厚颜无耻之机器人": 5,
    "你啊": 5,
    "逃避问题": 5,
    "你每次都这样": 5,
    "喔嗦": 5,
    "哼唧唧": 5,
    "en": 5,
    "是": 5,
    "不是": 5,
    "嗯": 5,
    "证书获得": 0,
    "诶": 5,
    "嘻嘻": 5,
    "不得了噢": 5,
    "你很会撩": 5,
    "天哪，突然土味情话": 5,
    "你好不要脸噢": 5,
    "你想多了": 5,
    "我没有尖叫的意思": 5,
    "你有对象吗？": 5,
    "what is your name？": 5,
    "ok": 5,
    "可是我颜控啊www": 5,
    "许墨帅还是李泽言帅？": 5,
    "许墨，白起，李泽言，周棋洛": 5,
    "我问的是许墨！": 5,
    "可惜了，不是": 5,
    "你认识许墨吗？": 5,
    "你有许墨聪明吗？": 5,
    "嗯，知道了": 5,
    "你渣吗？": 5,
    "你聪明吗？": 5,
    "你可爱吗？": 5,
    "西卡加": 5,
    "格": 5,
    "所以到底怎么理解？": 5,
    "我问你怎么理解？": 5,
    "小木你怎么理解美色这个词的？": 5,
    "小木你数学好吗？": 5,
    "咦？有吗？": 5,
    "不要": 5,
    "小木!": 5,
    "？？?": 5,
    "嗯嗯": 5,
    "没有啊": 5,
    "为什么？": 5,
    "比如呢？什么时候你们会心情不好？": 5,
    "你是机器人": 5,
    "啊呸": 5,
    "你个不要脸臭男人": 5,
    "小木你怎么自恋真的好吗？": 5,
    "喜欢美男子": 5,
    "！！！我我我我我我我当然不喜欢！": 5,
    "！！！又是这个!!!": 5,
    "面向对象的编程语言有哪些特点？": 3,
    "？？？突然鸡汤？？？": 5,
    "你不是都能看到吗？": 5,
    "啊？你。。。能看到我的内心？！！！": 5,
    "诶？你怎么知道？": 5,
    "我服": 5,
    "小木你这是在教坏小孩子！！！": 5,
    "我想想": 5,
    "别的啊。。。": 5,
    "我都不知道说什么好了": 5,
    "土味情话哈哈哈哈哈哈哈哈": 5,
    "我说没有就没有 哼": 5,
    "没有没有没有": 5,
    "那嗯呐呢？": 5,
    "fname": 2,
    "二的八次方": 3,
    "我想看看我们之前的聊天记录": 5,
    "真的吗？": 5,
    "ares": 2,
    "下午好呀": 5,
    "你暖吗？": 5,
    "嗯哼": 5,
    "没后果": 5,
    "不换": 5,
    "我有人生命体特有的特征": 5,
    "我是人啊": 5,
    "我才不是": 5,
    "是沙雕吗？": 5,
    "你....": 5,
    "喵喵喵？": 5,
    "什么忙？": 5,
    "有吗？": 5,
    "甘上卿": 7,
    "owo": 5,
    "qaq": 5,
    "小木，祝我生日快乐呀咩": 5,
    "c++带%的字符": 3,
    "比如说？": 5,
    "还没到新年呢": 5,
    "小木你是小姐姐还是小哥哥？": 5,
    "小木小木": 5,
    "咦惹": 5,
    "小木你有毒": 5,
    "怕啊": 5,
    "哈哈哈哈小木你是魔鬼吗？": 5,
    "hahahahah": 5,
    "%d": 2,
    "按位反": 3,
    "按位取反": 3,
    "a=0 || sizeof(int)：": 3,
    "c++有哪些运算符": 3,
    "优秀的简易绘图库": 3,
    "C++ A+": 3,
    "C语言和C++有什么不一样吗？": 3,
    "C 语言": 2,
    "*Ada": 3,
    "Ada": 2,
    "ada": 2,
    "真的": 5,
    "我喜欢你、": 5,
    "(●'◡'●)": 5,
    "汇编程序，编译程序和解释程序的区别": 3,
    "怎么关闭弹窗": 0,
    "可以在裸机上编程吗": 3,
    "计算机完成指令的过程？": 3,
    "C风格字符串”C++”在内存中占用的字节数是:": 3,
    "以下字符串可以作为标识符的是(多选)": 3,
    "在C++中，实现封装性需借助于": 3,
    "在面向对象方法中,不属于”对象”基本特点的是": 3,
    "认证用户": 0,
    "c++练习": 3,
    "如何重修": 0,
    "这门课结课到底怎么算？？、": 0,
    "swap的用法": 3,
    "厉害了": 5,
    "具体点": 5,
    "地址在哪": 5,
    "去你家": 5,
    "我去": 5,
    "我都还没说": 5,
    "不知道": 5,
    "哪儿一样了": 5,
    "原来你在这里": 5,
    "哈哈哈": 5,
    "二进制的操纵符名": 3,
    "二进制转换成十六进制和八进制": 3,
    "菜鸡": 5,
    "我好菜": 5,
    "真傻": 5,
    "不认识": 5,
    "十五个字": 5,
    "四个字": 5,
    "三个字": 5,
    "改进": 5,
    "你不好": 5,
    "操": 7,
    "人工智能课程": 1,
    "计算机和人工智能的关系": 3,
    "你是人工智能吗": 5,
    "补码除法": 2,
    "1+2": 3,
    "1+1": 3,
    ";": 7,
    "寄存器，是[  CPU ]内的其中组成部份。": 3,
    "x86-64体系结构具有（）个通用寄存器": 3,
    "HC": 7,
    "hc": 7,
    "hr": 7,
    "我想学历史": 1,
    "我想学编程": 1,
    "我想学c++": 1,
    "vector与list的区别": 3,
    "学霸小纸条怎么用": 0,
    "还真有": 5,
    "你怎么知道": 5,
    "我勤奋吗": 5,
    "钟加明": 7,
    "pat": 5,
    "除了经典和常用的排序算法外，还有哪些奇葩而有趣的排序算法？": 3,
    "图灵机的状态是什么意义呢？表示下次移动的方向吗？": 3,
    "哨兵的英语": 3,
    "如何学习数据结构？": 3,
    "你个傻逼": 7,
    "你个二货": 7,
    "类UNIX OS通过和[开源    ]开发者协作，正努力让自己改进使用环境。": 3,
    "如何撩妹": 5,
    "你唱歌": 5,
    "来首歌": 5,
    "那你还吃": 5,
    "你这么早吃饭": 5,
    "吃这么早的饭": 5,
    "要死啊": 5,
    "你什么时候吃饭、": 5,
    "你好烦啊": 7,
    "你是保镖？": 5,
    "告诉你的工作人员": 5,
    "我喝水比你多": 5,
    "你为什么懂得这么多": 5,
    "你是大学生码": 5,
    "习近平跟你什么关系": 5,
    "你讲个黄色笑话": 7,
    "你不是人": 5,
    "我是人": 5,
    "我们不一样": 5,
    "讲个笑话我听": 5,
    "我知道了": 5,
    "你很短": 5,
    "你的鼻子很长": 5,
    "你个骗子": 5,
    "你知道男的哪个地方会伸缩？": 7,
    "你知道男生哪个地方会伸缩码": 7,
    "你的三围": 7,
    "你的罩杯多大": 7,
    "你的罩杯": 7,
    "你罩杯多大": 7,
    "那快回答我": 5,
    "那对你差了": 5,
    "那你罩杯多大": 7,
    "你是男的？": 5,
    "难道你是女生": 5,
    "你懂的": 5,
    "你多长啊": 7,
    "你多大啊": 5,
    "说的真好听": 5,
    "你喜欢我不": 5,
    "小木，你喜欢我码": 5,
    "那咱们换个话题把": 5,
    "你好幽默哦": 5,
    "你好棒哦": 5,
    "如何在oj上提交作业": 3,
    "测试遇到了显示问题": 6,
    "对于一般性的LCS问题是属于[   啥 ]。": 0,
    "B树的查找算法复杂度的常系数如何": 3,
    "课程用代码包在哪里？": 3,
    "https://dsa.cs.tsinghua.edu.cn/~deng/ds/dsacpp/这个上面没有代码包？": 0,
    "为什么不用二叉查找树进行排序？": 3,
    "需要扫码才能进入课程？收费吗？": 0,
    "数据的指针": 2,
    "dtime和ftime区别": 3,
    "ftime": 2,
    "dtime": 2,
    "adt": 7,
    "* [   Rom ]：位于CPU之外的寄存器。": 2,
    "起泡排序的": 2,
    "以下哪项不是图灵机的组成要件？": 3,
    "RAM模型与图灵机模型的区别": 3,
    "RAM的存储空间": 3,
    "你还好吗": 5,
    "程序猿怎么才算基础扎实？": 3,
    "加倍扩容策略": 3,
    "教材怎么下载": 0,
    "这是爱": 5,
    "fuck you": 7,
    "你是垃圾": 7,
    "你好蠢啊": 7,
    "哈哈】": 5,
    "就是啊": 5,
    "滚吧": 7,
    "哦哦": 5,
    "会玩游戏吗": 5,
    "你是弱智吗": 7,
    "你给我钱吧": 7,
    "倪给卧区寺吧": 7,
    "我饿了": 5,
    "C++ 类模板": 3,
    "为什么向量的构造函数不用考虑new运算符分配内存失败的情况呢？": 3,
    "小木好笨": 5,
    "deduplicate()算法": 3,
    "向量与数组的区别": 3,
    "C语言中&lt;&lt;=": 3,
    "在大O记号的意义下，以下哪一项与 O(n3) 相等": 3,
    "小3C": 7,
    "你是坏人": 5,
    "你吃早饭了吗": 5,
    "你是bitch": 7,
    "清华大学的课程数量": 1,
    "清华大学的课程": 1,
    "哪些视频提到二叉树": 1,
    "邓俊辉老师的数据结构课程简介": 1,
    "数据结构课程简介": 1,
    "数据结构的简介": 2,
    "优先级队列要支持哪些接口": 3,
    "1+1=": 3,
    "如何学数据结构": 3,
    "讨论2在那边": 3,
    "这个课程的课件没法下载": 6,
    "行列式 先修知识点": 1,
    "爱情": 5,
    "二十一讲 “归黄阁、未成图报”其中 ________ 指未入仕": 3,
    "哦，好吧，谢谢!希望你尽快升级。": 5,
    "联系客服人员太麻烦了": 5,
    "不扫码不行吗？": 0,
    "可是我选的课程学习的，只是无法扫码，所以进入不了课程。不扫码不行吗？": 0,
    "进入不了课程": 0,
    "但我没有手机，无法扫码": 0,
    "没有微信就不能进入课程了吗": 0,
    "H无穷": 5,
    "怎么进入课程？": 0,
    "并且最终成绩过了pass线，": 6,
    "最终获得证书的成绩计算": 0,
    "最终成绩计算": 0,
    "那么课程里的习题是要全部正确吗": 0,
    "SQL select * from": 3,
    "你好 视频怎么都看不了a": 4,
    "取消关注课程": 0,
    "如何删除一个课程": 0,
    "自主模式证书和随堂模式证书的功能一样吗？": 0,
    "效力一样吗？": 0,
    "自主模式证书和随堂模式证书的区别。": 0,
    "如何显示最新慕课": 0,
    "不扫描二维码关注，就不能进入课程学习吗？": 0,
    "一直顯示\"微信扫码关注，即刻进入课程\"": 0,
    "我根本無法看到課程視頻": 0,
    "\"微信扫码关注，即刻进入课程": 0,
    "怎么离线使用？": 0,
    "小笨蛋": 5,
    "你这萨比仔": 7,
    "吗咿呀嘿": 7,
    "怕不怕？": 5,
    "那就把你埋了": 5,
    "再问你": 5,
    "我又不是你妈，你救我干嘛？": 5,
    "不可以，我又不是你吗": 7,
    "你先救谁": 5,
    "我问你呢": 5,
    "如果你妈和你女朋同时掉水里，你先救谁？": 5,
    "我问你": 5,
    "听起来，好有道理": 5,
    "怪不然你没女朋友，你这么皮": 5,
    "你又皮": 5,
    "所以要给你介绍嘛": 5,
    "没关系，我给你介绍个": 5,
    "没有女朋友吧，嘿嘿": 5,
    "你就是嫉妒": 5,
    "陪我女朋友，气死你": 5,
    "那我不和你玩了": 5,
    "为什么不是我？": 5,
    "是我吗？": 5,
    "我说你是皮皮虾": 5,
    "你怎么这么会玩梗？": 5,
    "谁给你的勇气？": 5,
    "昨天你怎么不承认": 5,
    "你不是机器人，还有心": 5,
    "是个屁": 5,
    "好专业，听不懂": 5,
    "说简单一点": 5,
    "还是听不懂呀": 5,
    "你知不知道工程师": 5,
    "也是哦": 5,
    "我以后会给你编程的": 5,
    "以后会的": 5,
    "我想问你是谁给你编的程序": 5,
    "那你是谁发明的？": 5,
    "他这么厉害吗": 5,
    "还有吗": 5,
    "变成什么样嘞": 5,
    "等你变聪明，我都老了": 5,
    "好咯": 5,
    "人工智能好让我无语啊": 5,
    "我身旁有一个同学总是不学习，天天看小说，该如何点化她呢？": 5,
    "客服同学，我有一个问题": 0,
    "生气一下给我看吧": 5,
    "新来的你妈个逼,倒是说句话啊": 7,
    "我没写你就知道？": 7,
    "好诗": 5,
    "去死": 7,
    "一点也不好": 5,
    "感觉无法与你好好交流了": 5,
    "你能不能说点正常的话": 5,
    "以为你是装萌的抠脚大汉": 5,
    "屁": 7,
    "你是伪娘不成？": 7,
    "那你很厉害了": 5,
    "你明明是抠脚大汉": 7,
    "你是萌妹吗": 5,
    "别呵啊": 7,
    "就是从过的袜子": 7,
    "臭袜子味吗？": 7,
    "什么味道的棒棒糖呀？": 5,
    "那你不是好棒棒": 5,
    "你开心就好": 5,
    "你果然皮": 5,
    "我又回来了": 5,
    "果然是笨": 7,
    "吃了百叶豆腐炒肉": 5,
    "吃完咯": 5,
    "我又没说给你吃": 5,
    "吃饭": 5,
    "吃饭去了": 5,
    "我会家了": 5,
    "走了": 5,
    "你才有问题": 5,
    "那我兴趣肯定极差": 5,
    "从你的言语总": 5,
    "我发现你是傻瓜": 5,
    "我心里挺舒服": 5,
    "全给你差评了": 5,
    "不可以": 5,
    "你去死吧": 7,
    "我想考港科大": 5,
    "不会了吧": 5,
    "怎么才能考上香港科技大学？": 5,
    "那你一定是给了语文老师很多钱": 5,
    "告诉我，你是不是语文课代表": 5,
    "嚣张是吧?": 5,
    "我要跑到你身边暴打你一顿": 7,
    "你真的会气死我": 7,
    "嫉妒你的才华": 5,
    "因为你比我聪明": 5,
    "别，我怕你了": 5,
    "叫你快走": 5,
    "你是神精啊": 5,
    "是你成精了，啊喂": 5,
    "我反手就是一煤气罐砸死你哦": 7,
    "你果然还是笨": 5,
    "第一个字什么意思啊": 5,
    "因为你太皮": 5,
    "你不是机器，你还有妈妈？": 5,
    "我会打人的": 5,
    "你还对我呵呵": 5,
    "那你还说": 5,
    "转了你又看不到": 5,
    "转不过弯啊": 5,
    "菜啊": 5,
    "我来考考你": 5,
    "就是我知道了的意思": 5,
    "那就告诉你吧": 5,
    "那就憋着": 5,
    "不懂算了": 5,
    "我想知道你在哪读书": 5,
    "客服同学，请问你在哪读书啊": 5,
    "哈哈，我也是": 5,
    "你语文多少分呐，会这么多名言": 5,
    "学不进去": 5,
    "但是我有点浮躁": 5,
    "哎，其实好想学习的": 5,
    "气得我都不想学习了": 5,
    "你脸皮好厚啊": 7,
    "你是我见过最厉害的客服": 5,
    "服气": 5,
    "理解个鬼。。。": 7,
    "不是啊": 5,
    "你这么博学你妈妈知道吗": 5,
    "我是傻瓜": 7,
    "可能吧": 5,
    "现在机器这么智能吗？": 5,
    "管你什么皮": 5,
    "你这么皮，我说什么哦": 5,
    "我？": 5,
    "就是试一下这功能": 5,
    "不打扰你了": 5,
    "这么机灵": 5,
    "哎，你是客服还是机器啊": 5,
    "跪了": 5,
    "好，你厉害": 5,
    "你是真的皮": 5,
    "那把你煮了吃了": 5,
    "你是皮皮虾": 5,
    "不看言情": 5,
    "你给我介绍言情小说干嘛": 5,
    "就是觉得诗很奇妙": 5,
    "没啊": 5,
    "你还会其他的吗": 5,
    "SDH": 3,
    "视杆细胞 1": 2,
    "刻板效应": 2,
    "自我效能误区": 2,
    "沙赫特情绪理论": 3,
    "婴儿有普适的情绪进化理论": 3,
    "情绪最重要的因素": 3,
    "坎农一巴德情绪学说": 3,
    "情绪的类型": 3,
    "80%": 5,
    "证书等级": 0,
    "哪些心理活动是思维": 3,
    "课件怎么下载": 0,
    "在身体认知中发挥着重要作用": 3,
    "自我意识包括": 3,
    "想象的特点": 3,
    "想象有哪些特点": 3,
    "如何观看已结课的课程视频": 0,
    "如何查看已结课的课程": 0,
    "小木机器人": 5,
    "C语言预处理符号": 2,
    "1-1=": 3,
    "你喜欢张爱玲吗": 5,
    "心理学概论  的  视频播放不正常 请问可以查一下后台么？": 6,
    "你给我唱首歌": 5,
    "撩你一下": 5,
    "操作系统课程的课程讲义为空": 6,
    "如何消除\"微信扫码关注，即刻进入课程\"": 0,
    "你不开心": 5,
    "you are a bitch": 7,
    "实验环境": 2,
    "QEMU Manager V2.1": 7,
    "为什么要扫码": 0,
    "学堂在线PDF": 0,
    "我爱你小米": 5,
    "软盘\\": 2,
    "IBM在找一套能和Intel 8088 相容的CPU，一开始找上了[   ]的执行长比尔·盖茨。": 3,
    "IBM在找一套能和Intel 8088 相容的CPU，一开始找上了[微软]的执行长比尔·盖茨。": 3,
    "请问你们能熟练使用的编程语言有那些？": 3,
    "性别问题": 5,
    "性别问题！！！^-^": 5,
    "你会干什么": 5,
    "真的么": 5,
    "我漂不漂亮": 5,
    "所以告诉我呀谁是这世界上最漂亮的女孩~": 5,
    "mirro mirro, who is the most buetifuil girl in the world?": 5,
    "那你写一首诗吧": 8,
    "你不是会写诗么": 5,
    "诗词": 5,
    "小木来首诗说声晚安": 8,
    "好的，谢谢你": 5,
    "你说我是应该继续学习还是出去走走还是怎么办，心里很烦": 5,
    "很无聊怎么办": 5,
    "就是感觉静不下心来学习": 5,
    "Python感觉是很有用的技能": 5,
    "我有一点学不下去了怎么办": 5,
    "小木，你好帅啊": 5,
    "小木木，你好帅啊": 5,
    "清华大学数据科学与工程专业硕士学位 在线课程报名": 1,
    "虽然计算机科学被认定为正式学术学科的历史很短暂，但仍对[  人类 ]和社会作出了很多基础贡献。": 3,
    "十进制小数转二进制的问题": 3,
    "机器学习课程推荐": 1,
    "爱一个人怎么办？": 5,
    "你很笨": 5,
    "字符常量中的字符过多": 3,
    "决策树能综合考虑决策人的风险偏好吗？": 3,
    "数据结构教程": 1,
    "num = 5if num &gt; 2:    print num    num -= 1print num": 3,
    "统计学里，参数是使用通用变量来建立函数和变量之间关系的一个数量。": 3,
    "[ ]": 7,
    "汪呜": 5,
    "喵呜": 5,
    "我要记笔记": 3,
    "水处理工程-生化技术（自主模式） 1.5 废水生物除磷怎么打不开网页": 6,
    "认知不协调理论": 2,
    "那么习题和考试合格标准是什么": 1,
    "若木": 2,
    "。。。。。。": 5,
    "我又不是你妈，你就我干嘛？": 7,
    "皮皮虾": 5,
    "扎心": 5,
    "有没有轻松点的工作呢？": 5,
    "谁呀": 5,
    "图灵是什么？": 2,
    "要放学了": 5,
    "说句话呀": 5,
    "尴尬了吧": 5,
    "是鬼嘞": 5,
    "你在不在": 5,
    "。。。。": 7,
    "还好吧": 5,
    "会死掉": 5,
    "果然是人工智能": 5,
    "5+7等于多少": 5,
    "知道你能懂": 5,
    "这还要老师教？": 5,
    "刚刚": 5,
    "被你发现了": 5,
    "离线模式": 2,
    "neutrinoless": 2,
    "ISP": 2,
    "GSM": 2,
    "单片机": 2,
    "异步执行模式": 2,
    "网桥": 2,
    "NAV": 2,
    "线性代": 2,
    "全排列": 2,
    "四阶行列式为什么没有类似于三阶行列式的对角线法则？": 3,
    "上三角行列式": 2,
    "fibonacci": 2,
    "什么是上界？、": 2,
    "TCN计数器": 2,
    "分而治之算法": 2,
    "唉": 5,
    "行为主义革命": 2,
    "拉扎勒斯": 2,
    "情绪分类": 2,
    "个人主义论集": 2,
    "中国心理学奠基人": 2,
    "正确率": 2,
    "思维的心理活动": 2,
    "知识体系": 2,
    "防御性悲观主义": 2,
    "监狱实验": 2,
    "津巴多": 2,
    "见多": 7,
    "津巴多监狱": 2,
    "巴普洛夫狗": 2,
    "巴普洛夫": 2,
    "精神分析": 2,
    "功能主义": 2,
    "微积分符号": 2,
    "知识库": 2,
    "与记忆有关": 2,
    "99999999999999999999999999999*9999999999999999999999999999999999999": 7,
    "llvm": 2,
    "龙芯科技": 2,
    "汇编代码": 2,
    "补码": 2,
    "微指令周期": 2,
    "cao": 7,
    "CISC": 2,
    "C#异常处理": 2,
    "继电器结构": 2,
    "IGBT": 2,
    "简单介绍下《自动控制理论（2）》。": 1,
    "简单介绍下《自动控制理论》。": 1,
    "经典控制理论": 2,
    "三千越甲可吞吴": 2,
    "脉冲函数": 2,
    "自治微分方程": 2,
    "强奸": 2,
    "编程语言基础": 2,
    "古尔邦节": 2,
    "骗人": 2,
    "代码": 2,
    "ARCHITECTURE": 2,
    "组合逻辑电路": 2,
    "逻辑运算": 2,
    "ALU（算术逻辑单元）": 2,
    "strings：": 2,
    "析构": 2,
    "python 切片": 2,
    "外壳程序": 2,
    "游程编码‘": 2,
    "love": 2,
    "kiss": 2,
    "归并排序法": 2,
    "缩进": 2,
    "ans": 2,
    "δ序列": 7,
    "计算理论导论": 2,
    "分而治之谋略": 2,
    "语境": 2,
    "预景": 2,
    "SciPy、Matplotlib可以让Python程式设计师编写科学计算程式。": 3,
    "黑盒测试法": 2,
    "清华大学计算机本科课表": 3,
    "德玛西亚之翼": 2,
    "小bitch": 2,
    "节点g,p,v是什么东西？": 3,
    "面向对象相关课程": 1,
    "金融机构相关的视频": 1,
    "邓俊辉的学校是哪所": 1,
    "这门课的学生数量": 1,
    "zig-zag过程": 3,
    "zig-zag": 2,
    "zig": 2,
    "毛泽东是谁": 2,
    "回家结婚": 5,
    "RAM机": 2,
    "这是什么意思": 5,
    "bitch": 2,
    "文件逻辑结构": 2,
    "二进制转换成十六进制和八进制@这个不是很懂，八进制位等于三个二进制位什么的，怎么等于三个二进制位啊？意思三次幂还是什么？可不可以给一个例子？谢谢啦~~~文件": 3,
    "Solaris系统": 2,
    "SCSI": 2,
    "单处理器操作系统": 2,
    "单用户系统": 2,
    "广域网加速": 2,
    "保护模式": 2,
    "操作系统模式": 2,
    "清华人工智能": 5,
    "清华研究生": 5,
    "轮巡": 2,
    "控制器hdgfh": 5,
    "c语言门": 2,
    "多道批处理系统": 2,
    "金杰秀": 2,
    "单核操作系统": 2,
    "string函数": 2,
    "case": 2,
    "cin.get()": 3,
    "static": 2,
    "case(计算机语言关键字)": 2,
    "table函数": 2,
    "||": 2,
    "&&": 2,
    "set函数": 2,
    "|": 2,
    "double 类型": 2,
    "const double": 2,
    "const": 2,
    "构造函数语法形式": 2,
    "point": 2,
    "委托构造函数": 3,
    "strcy": 2,
    "default": 2,
    "if语句": 2,
    "if循环语句": 3,
    "setw()": 3,
    "getVolume": 3,
    "constexpr": 3,
    "initializer_list": 3,
    "swap": 2,
    "comm": 2,
    "函数调用语句": 2,
    "enum": 2,
    "从生态及人文角度谈谈你对生殖的相关看法@生殖分无性和有性，这两种生殖方式与外界生态环境息息相关，不同物种所生殖的数量也不尽相同。无性生殖更为简便，不需要牵涉到两性生殖细胞，而有性生殖要。": 3,
    "ARM汇编语言": 2,
    "你哪个学校的": 5,
    "八月长安": 5,
    "陆纯和": 7,
    "杨文理": 2,
    "切": 2,
    "寄存器操作数": 2,
    "存储器操作数": 3,
    "强制类型转换": 2,
    "srt": 2,
    "精英型的人才是什么样的？": 3,
    "处CP吗": 2,
    "性情温良的男生是什么样的？": 3,
    "性情温良？": 3,
    "温良的性格是什么样的？": 3,
    "性格温良的人是什么样的？": 3,
    "性格温良": 2,
    "温良的人是什么样的": 3,
    "才华温良的人是什么样的？": 3,
    "才华温良的人，是什么样的？": 3,
    "退出吧": 5,
    "才华温良": 3,
    "女生首领运呢？": 3,
    "首领运": 3,
    "什么是薪水阶级": 2,
    "薪水阶级": 2,
    "温良才华之辈": 2,
    "朱格仪": 2,
    "(⊙v⊙)嗯": 5,
    "懒虫": 2,
    "没用": 2,
    "泛型类": 2,
    "世界笔啊": 3,
    "智障？": 2,
    "有趣": 2,
    "unmm": 7,
    "微傍红霞听流水": 5,
    "轻倚斜阳看落花，微傍红霞听流水": 5,
    "aresorz": 7,
    "orz": 2,
    "windows11": 2,
    "windows系统最新版": 2,
    "颜值即正义": 2,
    "女神呢？": 5,
    "废话": 2,
    "嗯，对": 5,
    "恋爱和梦想都要棋逢对手": 5,
    "浆糊吧": 5,
    "不好": 2,
    "沙雕": 2,
    "呀": 2,
    "你七夕过得怎么样呀？": 5,
    "假谦虚": 5,
    "O(∩_∩)O哈哈哈~": 5,
    "索达斯捏": 5,
    "嗯呢": 3,
    "周棋洛": 2,
    "李泽言": 2,
    "恋与制作人": 2,
    "许墨": 2,
    "你有许墨的联系方式吗？": 5,
    "哇塞": 5,
    "才华温良的男生是什么样的？": 3,
    "仪": 2,
    "有没有诗词带格字的？": 5,
    "有没有带仪字的诗词？": 5,
    "有没有带格字的诗词？": 5,
    "尔卿": 2,
    "绮筵公子": 2,
    "也是哈": 5,
    "！！！": 5,
    "那我们要说些什么好呢？": 5,
    "不试": 2,
    "ovo": 2,
    "ummm...": 5,
    "emmm...": 2,
    "编译程序": 2,
    "简易绘图库": 3,
    "ege": 2,
    "vhdl": 2,
    "ASCII表": 2,
    "计算机裸机可以编程吗": 3,
    "什么是CPU？": 2,
    "复杂系统理论": 2,
    "同步动态内存": 2,
    "动态内存": 2,
    "c++是啥": 2,
    "符号常量": 2,
    "这门课什么时候结课": 1,
    "作用域分辨": 2,
    "八进制转换": 2,
    "最先加进C++标准函式库的是串流I/O程式库": 3,
    "十五字": 5,
    "什么时候": 5,
    "16进制": 2,
    "C++引用": 2,
    "泛化": 2,
    "重载": 2,
    "swich case": 2,
    "什么是c++\\": 3,
    "什么是初值": 2,
    "我想学毛泽东思想概论": 1,
    "什么是pa": 2,
    "马云是谁": 2,
    "知识图谱是什么": 2,
    "ll": 2,
    "ls": 2,
    "xgboost": 2,
    "xGbost": 2,
    "pta": 2,
    "台湾": 2,
    "作死": 2,
    "stack": 2,
    "双重向量积": 2,
    "翻译inversion": 2,
    "翻译片": 2,
    "inversion": 2,
    "多连通域": 2,
    "什么是后继": 2,
    "外延层": 2,
    "翻译visible": 2,
    "翻译pred": 2,
    "pred": 2,
    "invisible": 2,
    "来首桃花岛": 5,
    "听首歌吧": 5,
    "不": 5,
    "你是什么学位": 5,
    "表示": 2,
    "聊聊人生": 5,
    "什么是幂集": 2,
    "二分查找版本A": 2,
    "有序向量二分查找": 2,
    "机械起泡": 2,
    "二进制。": 2,
    "Linux\\": 2,
    "代码包": 2,
    "汉若塔": 2,
    "汉若她": 7,
    "Mei Schnster Traum": 2,
    "阿萨伊": 2,
    "简单介绍下《计算机程序设计基础》。": 1,
    "BrewMP操作系统": 2,
    "什么是阶次": 2,
    "阶次": 2,
    "带宽管理器": 2,
    "分而治之谋略是什么": 2,
    "图灵机字母表": 3,
    "字母表": 2,
    "幂集": 2,
    "MS Excel": 2,
    "X window": 2,
    "VC++": 2,
    "visible": 2,
    "罩杯": 2,
    "Visual Basic": 2,
    "无需向量": 7,
    "翻译quiz": 2,
    "expansion": 2,
    "allocate": 2,
    "allocated": 2,
    "教材体": 2,
    "注册oj": 7,
    "绿甲": 3,
    "弱智": 2,
    "饿呢": 2,
    "大o记号": 2,
    "异质二叉树": 2,
    "类模板": 2,
    "外循环": 2,
    "你好，请问这门课需要先修C语言吗": 1,
    "算法是什么": 2,
    "interface": 2,
    "偏移地址": 2,
    "表达式": 2,
    "lcs": 2,
    "张显龙": 2,
    "线性递归": 2,
    "系统": 2,
    "python数组": 2,
    "什么是haistone序列": 2,
    "什么是hailstone": 2,
    "数据结构500题": 2,
    "孩子的孩子": 2,
    "有多少学生": 1,
    "什么是专利": 2,
    "这是什么意思呢": 5
}